pygritia/__init__.py
pygritia/attr.py
pygritia/binary.py
pygritia/call.py
pygritia/cases.py
pygritia/cast.py
pygritia/core.py
pygritia/item.py
pygritia/lazy.py
pygritia/ops.py
pygritia/prop.py
pygritia/py.typed
pygritia/rbinary.py
pygritia/symbols.py
pygritia/unary.py
pygritia/util.py
pygritia-0.2.0.dist-info/LICENSE
pygritia-0.2.0.dist-info/METADATA
pygritia-0.2.0.dist-info/WHEEL
pygritia-0.2.0.dist-info/top_level.txt
pygritia-0.2.0.dist-info/RECORD
