Metadata-Version: 2.1
Name: pygritia
Version: 0.2.0
Summary: Pygritia: Lazy Symbolic Evaluation
Home-page: https://github.com/gwangyi/pygritia
Author: Sungkwang Lee
Author-email: gwangyi.kr@gmail.com
License: MIT
Platform: UNKNOWN
Classifier: License :: OSI Approved :: MIT License
Classifier: Programming Language :: Python :: 3
Classifier: Programming Language :: Python :: 3.7
